tests/__init__.py
tests/test_server.py
tinyscp/__init__.py
tinyscp/cli.py
tinyscp/server.py
tinyscp-0.1.0.dist-info/licenses/LICENSE
tinyscp-0.1.0.dist-info/METADATA
tinyscp-0.1.0.dist-info/WHEEL
tinyscp-0.1.0.dist-info/entry_points.txt
tinyscp-0.1.0.dist-info/top_level.txt
tinyscp-0.1.0.dist-info/RECORD
