Metadata-Version: 2.4
Name: tinyscp
Version: 0.1.0
Summary: A minimal bidirectional SCP server for network automation
Author-email: Scott Peterman <scottpeterman@gmail.com>
License: MIT
Project-URL: Homepage, https://github.com/scottpeterman/tinyscp
Project-URL: Documentation, https://github.com/scottpeterman/tinyscp#readme
Project-URL: Repository, https://github.com/scottpeterman/tinyscp.git
Project-URL: Issues, https://github.com/scottpeterman/tinyscp/issues
Keywords: scp,ssh,file-transfer,network-automation,paramiko,server
Classifier: Development Status :: 4 - Beta
Classifier: Environment :: Console
Classifier: Intended Audience :: Developers
Classifier: Intended Audience :: System Administrators
Classifier: Intended Audience :: Telecommunications Industry
Classifier: License :: OSI Approved :: MIT License
Classifier: Operating System :: OS Independent
Classifier: Programming Language :: Python :: 3
Classifier: Programming Language :: Python :: 3.8
Classifier: Programming Language :: Python :: 3.9
Classifier: Programming Language :: Python :: 3.10
Classifier: Programming Language :: Python :: 3.11
Classifier: Programming Language :: Python :: 3.12
Classifier: Topic :: System :: Networking
Classifier: Topic :: System :: Systems Administration
Classifier: Topic :: Utilities
Requires-Python: >=3.8
License-File: LICENSE
Requires-Dist: paramiko>=2.7.0
Requires-Dist: pyyaml>=6.0.0
Provides-Extra: yaml
Requires-Dist: pyyaml>=5.0; extra == "yaml"
Provides-Extra: dev
Requires-Dist: pyyaml>=5.0; extra == "dev"
Requires-Dist: pytest>=7.0; extra == "dev"
Requires-Dist: pytest-cov>=4.0; extra == "dev"
Requires-Dist: black>=23.0; extra == "dev"
Requires-Dist: ruff>=0.1.0; extra == "dev"
Dynamic: license-file
